<?xml version="1.0" encoding="UTF-8"?>
<!-- generated: 2024-12-01T15:45:01+08:00 -->
<!-- generated by: 10049 [??] -->
<adag xmlns="http://pegasus.isi.edu/schema/DAX" xmlns:xsi="http://www.w3.org/2001/XMLSchema-instance" xsi:schemaLocation="http://pegasus.isi.edu/schema/DAX http://pegasus.isi.edu/schema/dax-2.1.xsd" version="2.1" count="1" index="0" name="test" jobCount="10" fileCount="0" childCount="5">
<!-- part 1: list of all referenced files (may be empty) -->
<!-- part 2: definition of all jobs (at least one) -->
  <job id="ID00000" namespace="CyberShake" name="ZipPSA" version="1.0" runtime="0.00">
    <uses file="PeakVals_FFI_0_1_ID00003.bsa" link="input" register="false" transfer="false" optional="false" type="data" size="474"/>
    <uses file="PeakVals_FFI_1_0_ID00006.bsa" link="input" register="false" transfer="false" optional="false" type="data" size="484"/>
    <uses file="PeakVals_FFI_1_0_ID00008.bsa" link="input" register="false" transfer="false" optional="false" type="data" size="234"/>
    <uses file="Cybershake_PSA.zip" link="output" register="true" transfer="true" optional="false" type="data" size="0"/>
  </job>
  <job id="ID00001" namespace="CyberShake" name="ZipSeis" version="1.0" runtime="0.00">
    <uses file="Seismogram_FFI_0_1_ID00003.grm" link="input" register="false" transfer="false" optional="false" type="data" size="249"/>
    <uses file="Seismogram_FFI_1_0_ID00006.grm" link="input" register="false" transfer="false" optional="false" type="data" size="504"/>
    <uses file="Seismogram_FFI_1_0_ID00008.grm" link="input" register="false" transfer="false" optional="false" type="data" size="128"/>
    <uses file="Cybershake_Seismograms.zip" link="output" register="true" transfer="true" optional="false" type="data" size="2"/>
  </job>
  <job id="ID00002" namespace="CyberShake" name="ExtractSGT" version="1.0" runtime="116.35">
    <uses file="FFI_0_1_f0.sgt" link="input" register="true" transfer="true" optional="false" type="data" size="203"/>
    <uses file="FFI_0_1_f1.sgt" link="input" register="true" transfer="true" optional="false" type="data" size="388"/>
    <uses file="FFI_0_1_txt.variation-s00192-h00281" link="input" register="true" transfer="true" optional="false" type="data" size="143"/>
  </job>
  <job id="ID00003" namespace="CyberShake" name="SeismogramSynthesis" version="1.0" runtime="26.90">
    <uses file="FFI_0_1_txt.variation-s00192-h00281" link="input" register="true" transfer="true" optional="false" type="data" size="143"/>
    <uses file="Seismogram_FFI_0_1_ID00003.grm" link="output" register="false" transfer="false" optional="false" type="data" size="249"/>
  </job>
  <job id="ID00004" namespace="CyberShake" name="PeakValCalcOkaya" version="1.0" runtime="0.81">
    <uses file="Seismogram_FFI_0_1_ID00003.grm" link="input" register="false" transfer="false" optional="false" type="data" size="225"/>
    <uses file="PeakVals_FFI_0_1_ID00003.bsa" link="output" register="false" transfer="false" optional="false" type="data" size="474"/>
  </job>
  <job id="ID00005" namespace="CyberShake" name="ExtractSGT" version="1.0" runtime="112.17">
    <uses file="FFI_1_0_f0.sgt" link="input" register="true" transfer="true" optional="false" type="data" size="356"/>
    <uses file="FFI_1_0_f1.sgt" link="input" register="true" transfer="true" optional="false" type="data" size="330"/>
    <uses file="FFI_1_0_txt.variation-s00174-h00081" link="input" register="true" transfer="true" optional="false" type="data" size="229"/>
  </job>
  <job id="ID00006" namespace="CyberShake" name="SeismogramSynthesis" version="1.0" runtime="54.96">
    <uses file="FFI_1_0_txt.variation-s00161-h00388" link="input" register="true" transfer="true" optional="false" type="data" size="241"/>
    <uses file="Seismogram_FFI_1_0_ID00006.grm" link="output" register="false" transfer="false" optional="false" type="data" size="504"/>
  </job>
  <job id="ID00007" namespace="CyberShake" name="PeakValCalcOkaya" version="1.0" runtime="1.23">
    <uses file="Seismogram_FFI_1_0_ID00006.grm" link="input" register="false" transfer="false" optional="false" type="data" size="82"/>
    <uses file="PeakVals_FFI_1_0_ID00006.bsa" link="output" register="false" transfer="false" optional="false" type="data" size="484"/>
  </job>
  <job id="ID00008" namespace="CyberShake" name="SeismogramSynthesis" version="1.0" runtime="25.35">
    <uses file="FFI_1_0_txt.variation-s00174-h00081" link="input" register="true" transfer="true" optional="false" type="data" size="229"/>
    <uses file="Seismogram_FFI_1_0_ID00008.grm" link="output" register="false" transfer="false" optional="false" type="data" size="128"/>
  </job>
  <job id="ID00009" namespace="CyberShake" name="PeakValCalcOkaya" version="1.0" runtime="1.21">
    <uses file="Seismogram_FFI_1_0_ID00008.grm" link="input" register="false" transfer="false" optional="false" type="data" size="95"/>
    <uses file="PeakVals_FFI_1_0_ID00008.bsa" link="output" register="false" transfer="false" optional="false" type="data" size="234"/>
  </job>
<!-- part 3: list of control-flow dependencies (may be empty) -->
  <child ref="ID00000">
    <parent ref="ID00004"/>
    <parent ref="ID00009"/>
    <parent ref="ID00007"/>
  </child>
  <child ref="ID00001">
    <parent ref="ID00006"/>
    <parent ref="ID00003"/>
    <parent ref="ID00008"/>
  </child>
  <child ref="ID00004">
    <parent ref="ID00003"/>
  </child>
  <child ref="ID00007">
    <parent ref="ID00006"/>
  </child>
  <child ref="ID00009">
    <parent ref="ID00008"/>
  </child>
</adag>
