<?xml version="1.0" encoding="UTF-8"?>
<!-- generated: 2024-12-01T15:45:02+08:00 -->
<!-- generated by: 10049 [??] -->
<adag xmlns="http://pegasus.isi.edu/schema/DAX" xmlns:xsi="http://www.w3.org/2001/XMLSchema-instance" xsi:schemaLocation="http://pegasus.isi.edu/schema/DAX http://pegasus.isi.edu/schema/dax-2.1.xsd" version="2.1" count="1" index="0" name="test" jobCount="10" fileCount="0" childCount="5">
<!-- part 1: list of all referenced files (may be empty) -->
<!-- part 2: definition of all jobs (at least one) -->
  <job id="ID00000" namespace="CyberShake" name="ZipPSA" version="1.0" runtime="0.00">
    <uses file="PeakVals_FFI_0_1_ID00003.bsa" link="input" register="false" transfer="false" optional="false" type="data" size="10"/>
    <uses file="PeakVals_FFI_0_2_ID00006.bsa" link="input" register="false" transfer="false" optional="false" type="data" size="68"/>
    <uses file="PeakVals_FFI_0_2_ID00008.bsa" link="input" register="false" transfer="false" optional="false" type="data" size="87"/>
    <uses file="Cybershake_PSA.zip" link="output" register="true" transfer="true" optional="false" type="data" size="2"/>
  </job>
  <job id="ID00001" namespace="CyberShake" name="ZipSeis" version="1.0" runtime="0.00">
    <uses file="Seismogram_FFI_0_1_ID00003.grm" link="input" register="false" transfer="false" optional="false" type="data" size="159"/>
    <uses file="Seismogram_FFI_0_2_ID00006.grm" link="input" register="false" transfer="false" optional="false" type="data" size="485"/>
    <uses file="Seismogram_FFI_0_2_ID00008.grm" link="input" register="false" transfer="false" optional="false" type="data" size="55"/>
    <uses file="Cybershake_Seismograms.zip" link="output" register="true" transfer="true" optional="false" type="data" size="2"/>
  </job>
  <job id="ID00002" namespace="CyberShake" name="ExtractSGT" version="1.0" runtime="151.93">
    <uses file="FFI_0_1_f0.sgt" link="input" register="true" transfer="true" optional="false" type="data" size="360"/>
    <uses file="FFI_0_1_f1.sgt" link="input" register="true" transfer="true" optional="false" type="data" size="148"/>
    <uses file="FFI_0_1_txt.variation-s00107-h00270" link="input" register="true" transfer="true" optional="false" type="data" size="343"/>
  </job>
  <job id="ID00003" namespace="CyberShake" name="SeismogramSynthesis" version="1.0" runtime="46.46">
    <uses file="FFI_0_1_txt.variation-s00107-h00270" link="input" register="true" transfer="true" optional="false" type="data" size="343"/>
    <uses file="Seismogram_FFI_0_1_ID00003.grm" link="output" register="false" transfer="false" optional="false" type="data" size="159"/>
  </job>
  <job id="ID00004" namespace="CyberShake" name="PeakValCalcOkaya" version="1.0" runtime="1.37">
    <uses file="Seismogram_FFI_0_1_ID00003.grm" link="input" register="false" transfer="false" optional="false" type="data" size="364"/>
    <uses file="PeakVals_FFI_0_1_ID00003.bsa" link="output" register="false" transfer="false" optional="false" type="data" size="10"/>
  </job>
  <job id="ID00005" namespace="CyberShake" name="ExtractSGT" version="1.0" runtime="106.40">
    <uses file="FFI_0_2_f0.sgt" link="input" register="true" transfer="true" optional="false" type="data" size="352"/>
    <uses file="FFI_0_2_f1.sgt" link="input" register="true" transfer="true" optional="false" type="data" size="117"/>
    <uses file="FFI_0_2_f2.sgt" link="input" register="true" transfer="true" optional="false" type="data" size="153"/>
    <uses file="FFI_0_2_f3.sgt" link="input" register="true" transfer="true" optional="false" type="data" size="93"/>
    <uses file="FFI_0_2_f4.sgt" link="input" register="true" transfer="true" optional="false" type="data" size="353"/>
    <uses file="FFI_0_2_txt.variation-s00289-h00321" link="input" register="true" transfer="true" optional="false" type="data" size="406"/>
  </job>
  <job id="ID00006" namespace="CyberShake" name="SeismogramSynthesis" version="1.0" runtime="39.53">
    <uses file="FFI_0_2_txt.variation-s00014-h00401" link="input" register="true" transfer="true" optional="false" type="data" size="447"/>
    <uses file="Seismogram_FFI_0_2_ID00006.grm" link="output" register="false" transfer="false" optional="false" type="data" size="485"/>
  </job>
  <job id="ID00007" namespace="CyberShake" name="PeakValCalcOkaya" version="1.0" runtime="0.75">
    <uses file="Seismogram_FFI_0_2_ID00006.grm" link="input" register="false" transfer="false" optional="false" type="data" size="445"/>
    <uses file="PeakVals_FFI_0_2_ID00006.bsa" link="output" register="false" transfer="false" optional="false" type="data" size="68"/>
  </job>
  <job id="ID00008" namespace="CyberShake" name="SeismogramSynthesis" version="1.0" runtime="50.85">
    <uses file="FFI_0_2_txt.variation-s00289-h00321" link="input" register="true" transfer="true" optional="false" type="data" size="406"/>
    <uses file="Seismogram_FFI_0_2_ID00008.grm" link="output" register="false" transfer="false" optional="false" type="data" size="55"/>
  </job>
  <job id="ID00009" namespace="CyberShake" name="PeakValCalcOkaya" version="1.0" runtime="0.86">
    <uses file="Seismogram_FFI_0_2_ID00008.grm" link="input" register="false" transfer="false" optional="false" type="data" size="190"/>
    <uses file="PeakVals_FFI_0_2_ID00008.bsa" link="output" register="false" transfer="false" optional="false" type="data" size="87"/>
  </job>
<!-- part 3: list of control-flow dependencies (may be empty) -->
  <child ref="ID00000">
    <parent ref="ID00004"/>
    <parent ref="ID00009"/>
    <parent ref="ID00007"/>
  </child>
  <child ref="ID00001">
    <parent ref="ID00006"/>
    <parent ref="ID00003"/>
    <parent ref="ID00008"/>
  </child>
  <child ref="ID00004">
    <parent ref="ID00003"/>
  </child>
  <child ref="ID00007">
    <parent ref="ID00006"/>
  </child>
  <child ref="ID00009">
    <parent ref="ID00008"/>
  </child>
</adag>
